cemirutils/__init__.py
cemirutils/utils.py
cemirutils-2.2.5.dist-info/LICENSE
cemirutils-2.2.5.dist-info/METADATA
cemirutils-2.2.5.dist-info/WHEEL
cemirutils-2.2.5.dist-info/top_level.txt
cemirutils-2.2.5.dist-info/RECORD
