Metadata-Version: 2.1
Name: cemirutils
Version: 2.2.5
Summary: Pythona yeni başlayanlar ve zaten kullananların yaptıkları işlerde vakit kazanmasını sağlayacak fonksiyon, metod, kütüphane ve dekoratörler...
Home-page: https://github.com/cememir/cemirutils
Author: Cem Emir Yüksektepe / Muslu Yüksektepe (musluyuksektepe@gmail.com)
Author-email: cememir2017@gmail.com
Classifier: Programming Language :: Python :: 3
Classifier: License :: OSI Approved :: MIT License
Classifier: Operating System :: OS Independent
Requires-Python: >=3.9
License-File: LICENSE
